README.md
setup.py
bin/iconv-chunks
bin/taskcat
bin/taskchecksetup
bin/taskcleanup
bin/taskconfig
bin/taskdeps
bin/taskdeps-dot
bin/taskdir
bin/taskdo
bin/taskdocs
bin/taskdu
bin/taskgc
bin/taskhash
bin/taskhead
bin/taskhelp
bin/taskhome
bin/taskimportcache
bin/taskinspect
bin/taskless
bin/taskls
bin/tasknames
bin/taskopen
bin/taskoutput
bin/taskps
bin/taskredo
bin/taskrm
bin/taskstatus
bin/tasktags
bin/tasktree
bin/taskversion
bin/taskwc
siskin/__init__.py
siskin/benchmark.py
siskin/cacheutils.py
siskin/common.py
siskin/configuration.py
siskin/conversions.py
siskin/database.py
siskin/decorator.py
siskin/filterconfig.py
siskin/mail.py
siskin/main.py
siskin/oai.py
siskin/openurl.py
siskin/task.py
siskin/test_conversions.py
siskin/test_openurl.py
siskin/test_utils.py
siskin/utils.py
siskin.egg-info/PKG-INFO
siskin.egg-info/SOURCES.txt
siskin.egg-info/dependency_links.txt
siskin.egg-info/entry_points.txt
siskin.egg-info/not-zip-safe
siskin.egg-info/requires.txt
siskin.egg-info/top_level.txt
siskin/assets/028_doaj_filter.tsv
siskin/assets/028_doaj_filter_issn.tsv
siskin/assets/8986.xml
siskin/assets/gbi_package_db_map_fulltext.tsv
siskin/assets/gbi_package_db_map_refs.tsv
siskin/assets/gbi_package_sigel_map.json
siskin/assets/55/tcid_amsl.tsv
siskin/assets/55/tcid_jstor.tsv
siskin/assets/68/68-fincjson
siskin/assets/87/87.flux
siskin/assets/87/87_morph.xml
siskin/assets/amsl/13587.json
siskin/assets/arxiv/121_morph.xml
siskin/assets/arxiv/arxiv.flux
siskin/assets/datacite/flux.flux
siskin/assets/datacite/morph.xml
siskin/assets/js/btoa.js
siskin/assets/mail/7049.tmpl
siskin/assets/maps/filemap_fincformat.tsv
siskin/assets/maps/filemap_rft.genre.tsv
siskin/assets/maps/sprachliste.tsv
siskin/assets/oai/flux.flux
siskin/assets/oai/morph.xml
siskin/sources/__init__.py
siskin/sources/amsl.py
siskin/sources/b3kat.py
siskin/sources/base.py
siskin/sources/cambridge.py
siskin/sources/ceeol.py
siskin/sources/core.py
siskin/sources/crossref.py
siskin/sources/datacite.py
siskin/sources/dblp.py
siskin/sources/ddnl.py
siskin/sources/degruyter.py
siskin/sources/doaj.py
siskin/sources/dummy.py
siskin/sources/eastview.py
siskin/sources/elsevierjournals.py
siskin/sources/genderopen.py
