Metadata-Version: 1.1
Name: siskin
Version: 1.3.9
Summary: Luigi tasks for building an article metadata index for https://finc.info
Home-page: https://github.com/ubleipzig/siskin
Author: The Finc Authors
Author-email: team@finc.info
License: UNKNOWN
Platform: UNKNOWN
Classifier: Development Status :: 4 - Beta
Classifier: Environment :: Console
Classifier: License :: OSI Approved :: GNU General Public License v3 (GPLv3)
Classifier: Operating System :: MacOS :: MacOS X
Classifier: Operating System :: POSIX
Classifier: Programming Language :: Python :: 3
Classifier: Programming Language :: Python
Classifier: Topic :: Text Processing
